jnpr/__init__.py
jnpr/jsnapy/__init__.py
jnpr/jsnapy/check.py
jnpr/jsnapy/content.html
jnpr/jsnapy/jsnapy.cfg
jnpr/jsnapy/jsnapy.py
jnpr/jsnapy/logging.yml
jnpr/jsnapy/notify.py
jnpr/jsnapy/operator.py
jnpr/jsnapy/setup_logging.py
jnpr/jsnapy/snap.py
jnpr/jsnapy/sqlite_get.py
jnpr/jsnapy/sqlite_store.py
jnpr/jsnapy/version.py
jnpr/jsnapy/xml_comparator.py
jsnapy-1.3.8.data/scripts/jsnap2py
jsnapy-1.3.8.dist-info/LICENSE
jsnapy-1.3.8.dist-info/METADATA
jsnapy-1.3.8.dist-info/WHEEL
jsnapy-1.3.8.dist-info/entry_points.txt
jsnapy-1.3.8.dist-info/top_level.txt
jsnapy-1.3.8.dist-info/RECORD
