Metadata-Version: 2.1
Name: jsnapy
Version: 1.3.8
Summary: Python version of Junos Snapshot Administrator
Home-page: http://www.github.com/Juniper/jsnapy
Author: Priyal Jain, Nitin Kumar
Author-email: jnpr-community-netdev@juniper.net
License: Apache 2.0
Keywords: Junos snapshot automation
Classifier: Environment :: Console
Classifier: Intended Audience :: Developers
Classifier: Intended Audience :: Information Technology
Classifier: Intended Audience :: System Administrators
Classifier: Intended Audience :: Telecommunications Industry
Classifier: License :: OSI Approved :: Apache Software License
Classifier: Operating System :: OS Independent
Classifier: Programming Language :: Python
Classifier: Programming Language :: Python :: 3.5
Classifier: Programming Language :: Python :: 3.6
Classifier: Programming Language :: Python :: 3.7
Classifier: Programming Language :: Python :: 3.8
Classifier: Topic :: Software Development :: Libraries
Classifier: Topic :: Software Development :: Libraries :: Application Frameworks
Classifier: Topic :: Software Development :: Libraries :: Python Modules
Classifier: Topic :: System :: Networking
Classifier: Topic :: Text Processing :: Markup :: XML
License-File: LICENSE
Requires-Dist: colorama
Requires-Dist: configparser
Requires-Dist: pyparsing
Requires-Dist: icdiff==1.9.1
Requires-Dist: future
Requires-Dist: lxml
Requires-Dist: junos-eznc
